django_paypal/__init__.py
django_paypal/admin.py
django_paypal/api_types.py
django_paypal/exceptions.py
django_paypal/models.py
django_paypal/ruff.toml
django_paypal/settings.py
django_paypal/signals.py
django_paypal/urls.py
django_paypal/utils.py
django_paypal/webhooks.py
django_paypal/wrappers.py
django_paypal/migrations/0001_initial.py
django_paypal/migrations/0002_auto_20171002_1551.py
django_paypal/migrations/0003_auto_20200124_1528.py
django_paypal/migrations/0004_paypalpayment_related_resource_state.py
django_paypal/migrations/0005_auto_20240207_0630.py
django_paypal/migrations/0006_auto_20240424_0727.py
django_paypal/migrations/0007_capture_id_for_direct_paypal_payment.py
django_paypal/migrations/0008_auto_20250409_1521.py
django_paypal/migrations/0009_auto_20250410_0631.py
django_paypal/migrations/__init__.py
django_paypal_plus-1.1.9.dist-info/licenses/LICENSE
django_paypal_plus-1.1.9.dist-info/METADATA
django_paypal_plus-1.1.9.dist-info/WHEEL
django_paypal_plus-1.1.9.dist-info/top_level.txt
django_paypal_plus-1.1.9.dist-info/RECORD
